scrapeAI/__init__.py
scrapeAI/web_scraper.py
scrapeAI/core/__init__.py
scrapeAI/core/base_scraper.py
scrapeAI/core/direct_scraper.py
scrapeAI/core/scraper_factory.py
scrapeAI/core/search_scraper.py
scrapeAI/llms/__init__.py
scrapeAI/llms/anthropic_llm.py
scrapeAI/llms/azure_openai_llm.py
scrapeAI/llms/base.py
scrapeAI/llms/google_llm.py
scrapeAI/llms/llm_factory.py
scrapeAI/llms/openai_llm.py
scrapeAI/utils/__init__.py
scrapeAI/utils/html_utils.py
scrapeAI/utils/logging.py
scrapeAI-0.3.0.dist-info/LICENSE
scrapeAI-0.3.0.dist-info/METADATA
scrapeAI-0.3.0.dist-info/WHEEL
scrapeAI-0.3.0.dist-info/top_level.txt
scrapeAI-0.3.0.dist-info/RECORD
