Metadata-Version: 2.1
Name: scrapeAI
Version: 0.3.0
Summary: A Python library to scrape web data using LLMs and Selenium
Home-page: https://github.com/deBUGger404/Scrape-AI
Author: Rakesh Kumar
Author-email: rakeshparmuwal1436@example.com
Classifier: Programming Language :: Python :: 3
Classifier: License :: OSI Approved :: MIT License
Classifier: Operating System :: OS Independent
Requires-Python: >=3.8
License-File: LICENSE
Requires-Dist: selenium
Requires-Dist: beautifulsoup4
Requires-Dist: anthropic
Requires-Dist: openai
Requires-Dist: google-generativeai
